{"dependencies":[],"generated":{"js":"module.exports=[{tfOpName:\"Add\",dlOpName:\"add\",category:\"arithmetic\",params:[{tfInputIndex:0,dlParamName:\"a\",type:\"tensor\"},{tfInputIndex:1,dlParamName:\"b\",type:\"tensor\"},{tfParamName:\"T\",dlParamName:\"dtype\",type:\"dtype\",notSupported:!0}]},{tfOpName:\"BiasAdd\",dlOpName:\"add\",category:\"arithmetic\",params:[{tfInputIndex:0,dlParamName:\"a\",type:\"tensor\"},{tfInputIndex:1,dlParamName:\"b\",type:\"tensor\"},{tfParamName:\"T\",dlParamName:\"dtype\",type:\"dtype\",notSupported:!0}]},{tfOpName:\"Sub\",dlOpName:\"sub\",category:\"arithmetic\",params:[{tfInputIndex:0,dlParamName:\"a\",type:\"tensor\"},{tfInputIndex:1,dlParamName:\"b\",type:\"tensor\"},{tfParamName:\"T\",dlParamName:\"dtype\",type:\"dtype\",notSupported:!0}]},{tfOpName:\"RealDiv\",dlOpName:\"div\",category:\"arithmetic\",params:[{tfInputIndex:0,dlParamName:\"a\",type:\"tensor\"},{tfInputIndex:1,dlParamName:\"b\",type:\"tensor\"},{tfParamName:\"T\",dlParamName:\"dtype\",type:\"dtype\",notSupported:!0}]},{tfOpName:\"Div\",dlOpName:\"div\",category:\"arithmetic\",params:[{tfInputIndex:0,dlParamName:\"a\",type:\"tensor\"},{tfInputIndex:1,dlParamName:\"b\",type:\"tensor\"},{tfParamName:\"T\",dlParamName:\"dtype\",type:\"dtype\",notSupported:!0}]},{tfOpName:\"Mul\",dlOpName:\"mul\",category:\"arithmetic\",params:[{tfInputIndex:0,dlParamName:\"a\",type:\"tensor\"},{tfInputIndex:1,dlParamName:\"b\",type:\"tensor\"},{tfParamName:\"T\",dlParamName:\"dtype\",type:\"dtype\",notSupported:!0}]},{tfOpName:\"Maximum\",dlOpName:\"maximum\",category:\"arithmetic\",params:[{tfInputIndex:0,dlParamName:\"a\",type:\"tensor\"},{tfInputIndex:1,dlParamName:\"b\",type:\"tensor\"}]},{tfOpName:\"Minimum\",dlOpName:\"minimum\",category:\"arithmetic\",params:[{tfInputIndex:0,dlParamName:\"a\",type:\"tensor\"},{tfInputIndex:1,dlParamName:\"b\",type:\"tensor\"}]},{tfOpName:\"Pow\",dlOpName:\"pow\",category:\"arithmetic\",params:[{tfInputIndex:0,dlParamName:\"a\",type:\"tensor\"},{tfInputIndex:1,dlParamName:\"b\",type:\"tensor\"},{tfParamName:\"T\",dlParamName:\"dtype\",type:\"dtype\",notSupported:!0}]},{tfOpName:\"SquaredDifference\",dlOpName:\"squaredDifference\",category:\"arithmetic\",params:[{tfInputIndex:0,dlParamName:\"a\",type:\"tensor\"},{tfInputIndex:1,dlParamName:\"b\",type:\"tensor\"},{tfParamName:\"T\",dlParamName:\"dtype\",type:\"dtype\",notSupported:!0}]},{tfOpName:\"Mod\",dlOpName:\"mod\",category:\"arithmetic\",params:[{tfInputIndex:0,dlParamName:\"a\",type:\"tensor\"},{tfInputIndex:1,dlParamName:\"b\",type:\"tensor\"},{tfParamName:\"T\",dlParamName:\"dtype\",type:\"dtype\",notSupported:!0}]}];"},"hash":"1ba9d556b7345be366aa5726c0df8572","cacheData":{}}