{"dependencies":[{"name":"/Users/apple/dev/project/ai4ar/.babelrc","includedInParent":true,"mtime":1527231222128},{"name":"/Users/apple/dev/project/ai4ar/package.json","includedInParent":true,"mtime":1528271787651}],"generated":{"js":"'use strict';\n\nObject.defineProperty(exports, \"__esModule\", {\n  value: true\n});\n/**\n * @license\n * Copyright 2018 Google LLC. All Rights Reserved.\n * Licensed under the Apache License, Version 2.0 (the \"License\");\n * you may not use this file except in compliance with the License.\n * You may obtain a copy of the License at\n *\n * http://www.apache.org/licenses/LICENSE-2.0\n *\n * Unless required by applicable law or agreed to in writing, software\n * distributed under the License is distributed on an \"AS IS\" BASIS,\n * WITHOUT WARRANTIES OR CONDITIONS OF ANY KIND, either express or implied.\n * See the License for the specific language governing permissions and\n * limitations under the License.\n * =============================================================================\n */\n\nvar IMAGENET_CLASSES = exports.IMAGENET_CLASSES = {\n  0: 'monitor',\n  1: 'pen',\n  2: 'keyboard',\n  3: 'laptop',\n  4: 'mouse',\n  5: 'backpack',\n  6: 'smartphone',\n  7: 'note'\n};","map":{"mappings":[{"generated":{"line":6,"column":0},"source":"imagenet_classes.js","original":{"line":1,"column":0}},{"generated":{"line":23,"column":0},"source":"imagenet_classes.js","original":{"line":18,"column":7}},{"name":"IMAGENET_CLASSES","generated":{"line":23,"column":4},"source":"imagenet_classes.js","original":{"line":18,"column":13}},{"generated":{"line":23,"column":50},"source":"imagenet_classes.js","original":{"line":18,"column":32}},{"generated":{"line":24,"column":0},"source":"imagenet_classes.js","original":{"line":19,"column":4}},{"generated":{"line":24,"column":5},"source":"imagenet_classes.js","original":{"line":19,"column":7}},{"generated":{"line":24,"column":14},"source":"imagenet_classes.js","original":{"line":18,"column":32}},{"generated":{"line":25,"column":0},"source":"imagenet_classes.js","original":{"line":20,"column":4}},{"generated":{"line":25,"column":5},"source":"imagenet_classes.js","original":{"line":20,"column":7}},{"generated":{"line":25,"column":10},"source":"imagenet_classes.js","original":{"line":18,"column":32}},{"generated":{"line":26,"column":0},"source":"imagenet_classes.js","original":{"line":21,"column":4}},{"generated":{"line":26,"column":5},"source":"imagenet_classes.js","original":{"line":21,"column":7}},{"generated":{"line":26,"column":15},"source":"imagenet_classes.js","original":{"line":18,"column":32}},{"generated":{"line":27,"column":0},"source":"imagenet_classes.js","original":{"line":22,"column":4}},{"generated":{"line":27,"column":5},"source":"imagenet_classes.js","original":{"line":22,"column":7}},{"generated":{"line":27,"column":13},"source":"imagenet_classes.js","original":{"line":18,"column":32}},{"generated":{"line":28,"column":0},"source":"imagenet_classes.js","original":{"line":23,"column":4}},{"generated":{"line":28,"column":5},"source":"imagenet_classes.js","original":{"line":23,"column":7}},{"generated":{"line":28,"column":12},"source":"imagenet_classes.js","original":{"line":18,"column":32}},{"generated":{"line":29,"column":0},"source":"imagenet_classes.js","original":{"line":24,"column":4}},{"generated":{"line":29,"column":5},"source":"imagenet_classes.js","original":{"line":24,"column":7}},{"generated":{"line":29,"column":15},"source":"imagenet_classes.js","original":{"line":18,"column":32}},{"generated":{"line":30,"column":0},"source":"imagenet_classes.js","original":{"line":25,"column":4}},{"generated":{"line":30,"column":5},"source":"imagenet_classes.js","original":{"line":25,"column":7}},{"generated":{"line":30,"column":17},"source":"imagenet_classes.js","original":{"line":18,"column":32}},{"generated":{"line":31,"column":0},"source":"imagenet_classes.js","original":{"line":26,"column":4}},{"generated":{"line":31,"column":5},"source":"imagenet_classes.js","original":{"line":26,"column":7}},{"generated":{"line":32,"column":0},"source":"imagenet_classes.js","original":{"line":18,"column":32}},{"generated":{"line":32,"column":1},"source":"imagenet_classes.js","original":{"line":18,"column":7}}],"sources":{"imagenet_classes.js":"/**\n * @license\n * Copyright 2018 Google LLC. All Rights Reserved.\n * Licensed under the Apache License, Version 2.0 (the \"License\");\n * you may not use this file except in compliance with the License.\n * You may obtain a copy of the License at\n *\n * http://www.apache.org/licenses/LICENSE-2.0\n *\n * Unless required by applicable law or agreed to in writing, software\n * distributed under the License is distributed on an \"AS IS\" BASIS,\n * WITHOUT WARRANTIES OR CONDITIONS OF ANY KIND, either express or implied.\n * See the License for the specific language governing permissions and\n * limitations under the License.\n * =============================================================================\n */\n\nexport const IMAGENET_CLASSES = {\n    0: 'monitor',\n    1: 'pen',\n    2: 'keyboard',\n    3: 'laptop',\n    4: 'mouse',\n    5: 'backpack',\n    6: 'smartphone',\n    7: 'note',\n};\n  "},"lineCount":null}},"hash":"0e4ca7f69f19aa05bc85e006c008201b","cacheData":{"env":{}}}